Metadata-Version: 2.1
Name: dash_loading_spinners
Version: 1.0.3
Summary: Fun and funky loading spinners for your Dash apps
Home-page: https://dash-loading-spinners.sproodlebuzz.co.uk/
Author: Gemma Down <gemmalsdown@icloud.com>
License: MIT
Project-URL: Bug Reports, https://github.com/glsdown/dash-loading-spinners/issues
Project-URL: Source, https://github.com/glsdown/dash-loading-spinners
Classifier: Framework :: Dash
Classifier: Development Status :: 5 - Production/Stable
Classifier: Programming Language :: Python :: 3.7
Classifier: Programming Language :: Python :: 3.8
Classifier: Programming Language :: Python :: 3.9
Classifier: Programming Language :: Python :: 3.10
Classifier: License :: OSI Approved :: MIT License
License-File: LICENSE
Requires-Dist: dash
